README.rst
setup.cfg
setup.py
attune_project_api/Exceptions.py
attune_project_api/ObjectStorageContext.py
attune_project_api/RelationField.py
attune_project_api/StorageTuple.py
attune_project_api/TupleFieldValidators.py
attune_project_api/TupleValidators.py
attune_project_api/__init__.py
attune_project_api/alembic.ini
attune_project_api/context_project_info.py
attune_project_api/key_util.py
attune_project_api/migration.py
attune_project_api.egg-info/PKG-INFO
attune_project_api.egg-info/SOURCES.txt
attune_project_api.egg-info/dependency_links.txt
attune_project_api.egg-info/not-zip-safe
attune_project_api.egg-info/requires.txt
attune_project_api.egg-info/top_level.txt
attune_project_api/_contexts/GitLibMixin.py
attune_project_api/_contexts/GitObjectStorageContext.py
attune_project_api/_contexts/__init__.py
attune_project_api/_private/RelationGraph.py
attune_project_api/_private/__init__.py
attune_project_api/_private/archive_format.py
attune_project_api/_private/archive_get_file_content.py
attune_project_api/_private/archive_hasher.py
attune_project_api/_private/archive_list_files.py
attune_project_api/_private/large_file_http_downloader.py
attune_project_api/_private/large_file_http_downloader_test.py
attune_project_api/_private/readme_compiler.py
attune_project_api/_private/website_compiler.py
attune_project_api/_private/website_compiler_test.py
attune_project_api/_private/templates/ProjectReadme.md.mako
attune_project_api/_private/templates/ProjectReadmeAttune.md.mako
attune_project_api/_private/templates/ProjectReadmeBlueprints.md.mako
attune_project_api/_private/templates/ProjectReadmeCloneInstructions.md.mako
attune_project_api/_private/templates/ProjectReadmeContribute.md.mako
attune_project_api/_private/templates/ProjectReadmeFiles.md.mako
attune_project_api/_private/templates/ProjectReadmeParameters.md.mako
attune_project_api/_private/templates/__init__.py
attune_project_api/_private/templates/project_website/ProjectWebsiteBlueprint.html.mako
attune_project_api/_private/templates/project_website/ProjectWebsiteBlueprintBreadcrumbs.html.mako
attune_project_api/_private/templates/project_website/ProjectWebsiteBlueprintHead.html.mako
