Metadata-Version: 2.1
Name: attune-project-api
Version: 24.2.3
Author: ServerTribe
Author-email: support@servertribe.com
Classifier: Programming Language :: Python :: 3.9
Requires-Dist: twisted
Requires-Dist: pygit2
Requires-Dist: vortexpy>=4.0.0
Requires-Dist: pytz
Requires-Dist: pathvalidate
Requires-Dist: py7zr
Requires-Dist: markdown
Requires-Dist: alembic
Requires-Dist: mako
Requires-Dist: sphinx
Requires-Dist: sphinx-rtd-theme
Requires-Dist: sphinx-autobuild
Requires-Dist: pytmpdir
